reynir/Greynir.grammar
reynir/__init__.py
reynir/_eparser.abi3.so
reynir/baseparser.py
reynir/basics.py
reynir/bindb.py
reynir/binparser.py
reynir/bintokenizer.py
reynir/cache.py
reynir/eparser.cpp
reynir/eparser.h
reynir/eparser_build.py
reynir/fastparser.py
reynir/glock.py
reynir/grammar.py
reynir/ifdtagger.py
reynir/incparser.py
reynir/lemmatize.py
reynir/matcher.py
reynir/nounphrase.py
reynir/py.typed
reynir/reducer.py
reynir/reynir.py
reynir/settings.py
reynir/simpletree.py
reynir/verbframe.py
reynir/config/Abbrev_errors.conf
reynir/config/AdjectivePredicates.conf
reynir/config/Adjectives.conf
reynir/config/GreynirEngine.conf
reynir/config/Names.conf
reynir/config/NounPredicates.conf
reynir/config/Phrases.conf
reynir/config/Prefs.conf
reynir/config/Prepositions.conf
reynir/config/Verbs.conf
reynir-3.6.1.dist-info/METADATA
reynir-3.6.1.dist-info/WHEEL
reynir-3.6.1.dist-info/top_level.txt
reynir-3.6.1.dist-info/zip-safe
reynir-3.6.1.dist-info/RECORD
reynir-3.6.1.dist-info/licenses/LICENSE.txt
