Metadata-Version: 2.4
Name: reynir
Version: 3.6.1
Summary: A natural language parser for Icelandic
Author-email: "Miðeind ehf." <mideind@mideind.is>
Maintainer-email: "Miðeind ehf." <mideind@mideind.is>
License: MIT License
Project-URL: Repository, https://github.com/mideind/GreynirEngine
Project-URL: Homepage, https://greynir.is
Project-URL: Documentation, https://greynir.is/doc/
Project-URL: Issues, https://github.com/mideind/GreynirEngine/issues
Keywords: nlp,parser,icelandic
Classifier: Development Status :: 5 - Production/Stable
Classifier: Intended Audience :: Developers
Classifier: Intended Audience :: Science/Research
Classifier: License :: OSI Approved :: MIT License
Classifier: Operating System :: Unix
Classifier: Operating System :: POSIX
Classifier: Operating System :: Microsoft :: Windows
Classifier: Operating System :: MacOS
Classifier: Natural Language :: Icelandic
Classifier: Programming Language :: Python
Classifier: Programming Language :: Python :: 3
Classifier: Programming Language :: Python :: 3.9
Classifier: Programming Language :: Python :: 3.10
Classifier: Programming Language :: Python :: 3.11
Classifier: Programming Language :: Python :: 3.12
Classifier: Programming Language :: Python :: 3.13
Classifier: Programming Language :: Python :: 3.14
Classifier: Programming Language :: Python :: Implementation :: CPython
Classifier: Programming Language :: Python :: Implementation :: PyPy
Classifier: Topic :: Software Development :: Libraries :: Python Modules
Classifier: Topic :: Utilities
Classifier: Topic :: Text Processing :: Linguistic
Requires-Python: >=3.9
License-File: LICENSE.txt
Requires-Dist: cffi>=1.17.1
Requires-Dist: tokenizer>=3.6.0
Requires-Dist: islenska>=1.0.4
Requires-Dist: typing_extensions
Provides-Extra: dev
Requires-Dist: pytest; extra == "dev"
Requires-Dist: setuptools; extra == "dev"
Dynamic: license-file
